abacus/__info__.py
abacus/__init__.py
abacus/__main__.py
abacus/basic.py
abacus/ipython.py
abacus/main.py
abacus/shell.py
abacus/tokenizer.py
abacus/transformer.py
abacus/basic_shell/__init__.py
abacus/basic_shell/basic_shell.py
abacus/basic_shell/main.py
abacus/ipython_shell/__init__.py
abacus/ipython_shell/ipython_shell.py
abacus/ipython_shell/main.py
abacus/ipython_shell/aliases/__init__.py
abacus/ipython_shell/aliases/aliases.py
abacus/ipython_shell/prompt/__init__.py
abacus/ipython_shell/prompt/prompt.py
abacus/ns/__init__.py
abacus/ns/init.pyi
abacus/test/__init__.py
abacus/test/__main__.py
abacus/test/test_tokenization.py
abacus_icalc-0.2.3.dist-info/METADATA
abacus_icalc-0.2.3.dist-info/WHEEL
abacus_icalc-0.2.3.dist-info/entry_points.txt
abacus_icalc-0.2.3.dist-info/license_files/LICENSE
abacus_icalc-0.2.3.dist-info/RECORD
