Metadata-Version: 2.1
Name: abacus-icalc
Version: 0.2.3
Summary: An interactive algebra calculator built in Python using Python
Project-URL: Home, https://sandorex.github.io/abacus
Project-URL: Source, https://github.com/sandorex/abacus
Author-email: Aleksandar Radivojevic <rzhw3h@gmail.com>
Classifier: Development Status :: 4 - Beta
Classifier: Environment :: Console
Classifier: Framework :: IPython
Classifier: License :: OSI Approved :: GNU General Public License v3 or later (GPLv3+)
Requires-Python: ~=3.8
Requires-Dist: sympy~=1.9
Provides-Extra: ipython
Requires-Dist: ipython~=7.21; extra == 'ipython'
